JoPasteOutbreak/__init__.py
JoPasteOutbreak/city.py
JoPasteOutbreak/event_card.py
JoPasteOutbreak/virus.py
JoPaste_Outbreak-1.1.1.dist-info/LICENCE.txt
JoPaste_Outbreak-1.1.1.dist-info/METADATA
JoPaste_Outbreak-1.1.1.dist-info/WHEEL
JoPaste_Outbreak-1.1.1.dist-info/top_level.txt
JoPaste_Outbreak-1.1.1.dist-info/RECORD
