Metadata-Version: 2.1
Name: JoPaste-Outbreak
Version: 1.1.1
Summary: Simulating covid outbreak
Author: JoshuaPaste (Joshua Payte)
Author-email: Joshua@peerlogic.com
Classifier: Programming Language :: Python :: 3
Classifier: License :: OSI Approved :: MIT License
Classifier: Operating System :: Unix
Classifier: Operating System :: MacOS :: MacOS X
Classifier: Operating System :: Microsoft :: Windows
Requires-Python: >=3.10
License-File: LICENCE.txt
